{
  "펄어비스": {
    "_alert_cfg": {
      "target": 48000.0,
      "stoplos": 38000.0,
      "trailing_pct": 10.0
    },
    "last_price": 39950,
    "last_checked": "2026-06-16 13:02:59",
    "fired": [
      "trailing"
    ]
  },
  "현대자동차": {
    "_alert_cfg": {
      "target": 700000.0,
      "stoplos": 650000.0,
      "trailing_pct": 10.0
    },
    "last_price": 641000,
    "last_checked": "2026-06-16 13:02:59",
    "fired": [
      "stoplos"
    ]
  },
  "삼성전자": {
    "_alert_cfg": {
      "target": 360000.0,
      "stoplos": 320000.0,
      "trailing_pct": 10.0
    },
    "last_price": 342000,
    "last_checked": "2026-06-16 13:02:59",
    "fired": []
  },
  "LG이노텍": {
    "_alert_cfg": {
      "target": 1300000.0,
      "stoplos": 1050000.0,
      "trailing_pct": 10.0
    },
    "high_since_buy": 1277000,
    "last_price": 1265000,
    "last_checked": "2026-06-16 13:02:59",
    "fired": [
      "near_target"
    ]
  }
}